pywxm-1.1.3.dist-info/METADATA
pywxm-1.1.3.dist-info/WHEEL
pywxm-1.1.3.dist-info/entry_points.txt
pywxm-1.1.3.dist-info/licenses/LICENSE
pywxm/__init__.py
pywxm/api.py
pywxm/model.py
pywxm/py.typed
pywxm-1.1.3.dist-info/RECORD
