Metadata-Version: 2.1
Name: pywxm
Version: 1.1.3
Summary: AsyncIO Python SDK for WeatherXM
Author-Email: TheNoctambulist <thenoctambulist@zoho.com>
License: MIT
Classifier: Development Status :: 5 - Production/Stable
Classifier: Intended Audience :: Developers
Classifier: Programming Language :: Python :: 3.11
Classifier: Programming Language :: Python :: 3.12
Classifier: Framework :: AsyncIO
Classifier: Typing :: Typed
Classifier: Operating System :: OS Independent
Classifier: License :: OSI Approved :: MIT License
Project-URL: Homepage, https://github.com/thenoctambulist/pywxm
Project-URL: Issues, https://github.com/thenoctambulist/pywxm/issues
Requires-Python: >=3.11
Requires-Dist: aiohttp>=3.11.11
Requires-Dist: pyjwt>=2.10.1
